{
  "location": "Totnes",
  "slug": "totnes",
  "generatedAt": "2026-07-23T09:57:23.571Z",
  "count": 30,
  "properties": [
    {
      "title": "2 bedroom flat for sale",
      "price": 170000,
      "address": "St. Katherines Mews, St. Katherines Way, Totnes, Devon, TQ9",
      "bedrooms": 2,
      "bathrooms": null,
      "sqft": null,
      "postedDate": null,
      "agent": "Fulfords - Totnes",
      "agentPhone": "01803 268438",
      "type": "Flat",
      "description": "",
      "images": [
        "https://media.onthemarket.com/properties/18703169/1593849528/image-0-480x320.jpg",
        "https://media.onthemarket.com/properties/18703169/1593849528/image-1-480x320.jpg",
        "https://media.onthemarket.com/properties/18703169/1593849528/image-2-480x320.jpg",
        "https://media.onthemarket.com/properties/18703169/1593849528/image-3-480x320.jpg",
        "https://media.onthemarket.com/properties/18703169/1593849528/image-4-480x320.jpg"
      ],
      "sources": [
        {
          "portal": "OnTheMarket",
          "url": "https://www.onthemarket.com/details/18703169/"
        }
      ],
      "lat": 50.41663565421549,
      "lon": -3.6912134759871997,
      "searchLocation": "Totnes",
      "searchLocations": [
        "Totnes"
      ],
      "autoRejected": false,
      "geoAccuracy": "postcode",
      "nearestAirport": {
        "name": "Exeter International Airport",
        "icao": "EGTE",
        "category": "airport",
        "usage": "commercial",
        "active": true,
        "distanceKm": 40.38102164109834,
        "distanceMiles": 25.09159579815092
      },
      "nearestAirstrip": {
        "name": "Halwell Airstrip",
        "icao": null,
        "category": "airstrip",
        "usage": "private",
        "active": false,
        "distanceKm": 5.828236845808926,
        "distanceMiles": 3.6214973571171383
      },
      "nearestHeliport": {
        "name": "Torquay Go-Kart circuit helipad",
        "icao": null,
        "category": "heliport",
        "usage": "private",
        "active": false,
        "distanceKm": 10.220867620855508,
        "distanceMiles": 6.350950734438608
      },
      "minAirportDistanceMiles": 3.6214973571171383,
      "flyoverRef": {
        "location": "London Gatwick Area",
        "flightsPerDay": 688.1,
        "seasonalFlag": "stable",
        "generatedAt": "2026-06-26T12:59:20.862Z"
      },
      "keywordsMatched": 0,
      "baselineComparison": {
        "airportsCount": 0,
        "airstripsCount": 2,
        "helipadsCount": 2,
        "airportsDiff": -4,
        "airstripsDiff": 2,
        "helipadsDiff": -2,
        "flightsPerDay": 688.1,
        "flightsDiffPct": 715
      },
      "isNew": true,
      "retrievedAt": "2026-07-23T09:57:23.571Z"
    },
    {
      "title": "4 bedroom semi-detached house for sale",
      "price": 425000,
      "address": "Mill Tail, Totnes",
      "bedrooms": 4,
      "bathrooms": null,
      "sqft": null,
      "postedDate": null,
      "agent": "Woods - South Devon",
      "agentPhone": "01626 295881",
      "type": "Semi-detached house",
      "description": "",
      "images": [
        "https://media.onthemarket.com/properties/19972120/1630826398/image-0-480x320.jpg",
        "https://media.onthemarket.com/properties/19972120/1630826398/image-1-480x320.jpg",
        "https://media.onthemarket.com/properties/19972120/1630826398/image-2-480x320.jpg",
        "https://media.onthemarket.com/properties/19972120/1630826398/image-3-480x320.jpg",
        "https://media.onthemarket.com/properties/19972120/1630826398/image-4-480x320.jpg"
      ],
      "sources": [
        {
          "portal": "OnTheMarket",
          "url": "https://www.onthemarket.com/details/19972120/"
        }
      ],
      "lat": 50.4314634,
      "lon": -3.6835401,
      "searchLocation": "Totnes",
      "searchLocations": [
        "Totnes"
      ],
      "autoRejected": true,
      "geoAccuracy": "address",
      "nearestAirport": {
        "name": "Exeter International Airport",
        "icao": "EGTE",
        "category": "airport",
        "usage": "commercial",
        "active": true,
        "distanceKm": 38.67617355376496,
        "distanceMiles": 24.03225263727649
      },
      "nearestAirstrip": {
        "name": "Marldon Airstrip",
        "icao": null,
        "category": "airstrip",
        "usage": "private",
        "active": false,
        "distanceKm": 6.280679164138018,
        "distanceMiles": 3.9026318928996044
      },
      "nearestHeliport": {
        "name": "Torquay Go-Kart circuit helipad",
        "icao": null,
        "category": "heliport",
        "usage": "private",
        "active": false,
        "distanceKm": 10.239328927674293,
        "distanceMiles": 6.362422055117904
      },
      "minAirportDistanceMiles": 3.9026318928996044,
      "flyoverRef": {
        "location": "London Gatwick Area",
        "flightsPerDay": 688.1,
        "seasonalFlag": "stable",
        "generatedAt": "2026-06-26T12:59:20.862Z"
      },
      "keywordsMatched": 0,
      "baselineComparison": {
        "airportsCount": 0,
        "airstripsCount": 2,
        "helipadsCount": 2,
        "airportsDiff": -4,
        "airstripsDiff": 2,
        "helipadsDiff": -2,
        "flightsPerDay": 688.1,
        "flightsDiffPct": 715
      },
      "isNew": true,
      "retrievedAt": "2026-07-23T09:57:23.571Z"
    },
    {
      "title": "2 bedroom apartment for sale",
      "price": 280000,
      "address": "The Plains, Totnes",
      "bedrooms": 2,
      "bathrooms": null,
      "sqft": null,
      "postedDate": null,
      "agent": "Stags - Totnes",
      "agentPhone": "01803 268823",
      "type": "Apartment",
      "description": "Spacious second floor waterside apartmentHighly convenient central Totnes locationViews towards the River DartStags - TotnesAdded > 14 daysEmail01803 268823",
      "images": [
        "https://media.onthemarket.com/properties/19842896/1626382706/image-0-480x320.jpg",
        "https://media.onthemarket.com/properties/19842896/1626382706/image-1-480x320.jpg",
        "https://media.onthemarket.com/properties/19842896/1626383033/image-2-480x320.jpg",
        "https://media.onthemarket.com/properties/19842896/1626383033/image-3-480x320.jpg",
        "https://media.onthemarket.com/properties/19842896/1626384422/image-4-480x320.jpg"
      ],
      "sources": [
        {
          "portal": "OnTheMarket",
          "url": "https://www.onthemarket.com/details/19842896/"
        }
      ],
      "lat": 50.4303453,
      "lon": -3.6834947,
      "searchLocation": "Totnes",
      "searchLocations": [
        "Totnes"
      ],
      "autoRejected": false,
      "geoAccuracy": "address",
      "nearestAirport": {
        "name": "Exeter International Airport",
        "icao": "EGTE",
        "category": "airport",
        "usage": "commercial",
        "active": true,
        "distanceKm": 38.78299234469322,
        "distanceMiles": 24.09862673621437
      },
      "nearestAirstrip": {
        "name": "Marldon Airstrip",
        "icao": null,
        "category": "airstrip",
        "usage": "private",
        "active": false,
        "distanceKm": 6.343653946998475,
        "distanceMiles": 3.9417625967003893
      },
      "nearestHeliport": {
        "name": "Torquay Go-Kart circuit helipad",
        "icao": null,
        "category": "heliport",
        "usage": "private",
        "active": false,
        "distanceKm": 10.186984451077846,
        "distanceMiles": 6.329896715350692
      },
      "minAirportDistanceMiles": 3.9417625967003893,
      "flyoverRef": {
        "location": "London Gatwick Area",
        "flightsPerDay": 688.1,
        "seasonalFlag": "stable",
        "generatedAt": "2026-06-26T12:59:20.862Z"
      },
      "keywordsMatched": 0,
      "baselineComparison": {
        "airportsCount": 0,
        "airstripsCount": 2,
        "helipadsCount": 2,
        "airportsDiff": -4,
        "airstripsDiff": 2,
        "helipadsDiff": -2,
        "flightsPerDay": 688.1,
        "flightsDiffPct": 715
      },
      "isNew": true,
      "retrievedAt": "2026-07-23T09:57:23.571Z"
    },
    {
      "title": "2 bedroom flat for sale",
      "price": 315000,
      "address": "Fore Street, Totnes, TQ9",
      "bedrooms": 2,
      "bathrooms": null,
      "sqft": null,
      "postedDate": null,
      "agent": "Purplebricks -  Covering Torquay",
      "agentPhone": "01803 268033",
      "type": "Flat",
      "description": "",
      "images": [
        "https://media.onthemarket.com/properties/19780489/1623718179/image-0-480x320.jpg",
        "https://media.onthemarket.com/properties/19780489/1623718179/image-1-480x320.jpg",
        "https://media.onthemarket.com/properties/19780489/1623718179/image-2-480x320.jpg",
        "https://media.onthemarket.com/properties/19780489/1623718179/image-3-480x320.jpg",
        "https://media.onthemarket.com/properties/19780489/1623718179/image-4-480x320.jpg"
      ],
      "sources": [
        {
          "portal": "OnTheMarket",
          "url": "https://www.onthemarket.com/details/19780489/"
        }
      ],
      "lat": 50.41663565421549,
      "lon": -3.6912134759871997,
      "searchLocation": "Totnes",
      "searchLocations": [
        "Totnes"
      ],
      "autoRejected": false,
      "geoAccuracy": "postcode",
      "nearestAirport": {
        "name": "Exeter International Airport",
        "icao": "EGTE",
        "category": "airport",
        "usage": "commercial",
        "active": true,
        "distanceKm": 40.38102164109834,
        "distanceMiles": 25.09159579815092
      },
      "nearestAirstrip": {
        "name": "Halwell Airstrip",
        "icao": null,
        "category": "airstrip",
        "usage": "private",
        "active": false,
        "distanceKm": 5.828236845808926,
        "distanceMiles": 3.6214973571171383
      },
      "nearestHeliport": {
        "name": "Torquay Go-Kart circuit helipad",
        "icao": null,
        "category": "heliport",
        "usage": "private",
        "active": false,
        "distanceKm": 10.220867620855508,
        "distanceMiles": 6.350950734438608
      },
      "minAirportDistanceMiles": 3.6214973571171383,
      "flyoverRef": {
        "location": "London Gatwick Area",
        "flightsPerDay": 688.1,
        "seasonalFlag": "stable",
        "generatedAt": "2026-06-26T12:59:20.862Z"
      },
      "keywordsMatched": 0,
      "baselineComparison": {
        "airportsCount": 0,
        "airstripsCount": 2,
        "helipadsCount": 2,
        "airportsDiff": -4,
        "airstripsDiff": 2,
        "helipadsDiff": -2,
        "flightsPerDay": 688.1,
        "flightsDiffPct": 715
      },
      "isNew": true,
      "retrievedAt": "2026-07-23T09:57:23.571Z"
    },
    {
      "title": "3 bedroom terraced house for sale",
      "price": 350000,
      "address": "Bank Lane, Totnes",
      "bedrooms": 3,
      "bathrooms": null,
      "sqft": null,
      "postedDate": null,
      "agent": "Stags - Totnes",
      "agentPhone": "01803 268823",
      "type": "Terraced house",
      "description": "",
      "images": [
        "https://media.onthemarket.com/properties/19439790/1621183163/image-0-480x320.jpg",
        "https://media.onthemarket.com/properties/19439790/1621183163/image-1-480x320.jpg",
        "https://media.onthemarket.com/properties/19439790/1621183163/image-2-480x320.jpg",
        "https://media.onthemarket.com/properties/19439790/1621183163/image-3-480x320.jpg",
        "https://media.onthemarket.com/properties/19439790/1621183163/image-4-480x320.jpg"
      ],
      "sources": [
        {
          "portal": "OnTheMarket",
          "url": "https://www.onthemarket.com/details/19439790/"
        }
      ],
      "lat": 50.4304965,
      "lon": -3.6845145,
      "searchLocation": "Totnes",
      "searchLocations": [
        "Totnes"
      ],
      "autoRejected": true,
      "geoAccuracy": "address",
      "nearestAirport": {
        "name": "Exeter International Airport",
        "icao": "EGTE",
        "category": "airport",
        "usage": "commercial",
        "active": true,
        "distanceKm": 38.80372033103736,
        "distanceMiles": 24.111506505817015
      },
      "nearestAirstrip": {
        "name": "Marldon Airstrip",
        "icao": null,
        "category": "airstrip",
        "usage": "private",
        "active": false,
        "distanceKm": 6.395864437645537,
        "distanceMiles": 3.974204681484245
      },
      "nearestHeliport": {
        "name": "Torquay Go-Kart circuit helipad",
        "icao": null,
        "category": "heliport",
        "usage": "private",
        "active": false,
        "distanceKm": 10.260034274264616,
        "distanceMiles": 6.375287757034078
      },
      "minAirportDistanceMiles": 3.974204681484245,
      "flyoverRef": {
        "location": "London Gatwick Area",
        "flightsPerDay": 688.1,
        "seasonalFlag": "stable",
        "generatedAt": "2026-06-26T12:59:20.862Z"
      },
      "keywordsMatched": 0,
      "baselineComparison": {
        "airportsCount": 0,
        "airstripsCount": 2,
        "helipadsCount": 2,
        "airportsDiff": -4,
        "airstripsDiff": 2,
        "helipadsDiff": -2,
        "flightsPerDay": 688.1,
        "flightsDiffPct": 715
      },
      "isNew": true,
      "retrievedAt": "2026-07-23T09:57:23.571Z"
    },
    {
      "title": "2 bedroom terraced house for sale",
      "price": 375000,
      "address": "South Street, Totnes, Devon.",
      "bedrooms": 2,
      "bathrooms": null,
      "sqft": null,
      "postedDate": null,
      "agent": "Sample Mills - Newton Abbott",
      "agentPhone": "01626 295554",
      "type": "Terraced house",
      "description": "",
      "images": [
        "https://media.onthemarket.com/properties/18927245/1598253333/image-0-480x320.jpg",
        "https://media.onthemarket.com/properties/18927245/1620557935/image-1-480x320.jpg",
        "https://media.onthemarket.com/properties/18927245/1620557935/image-2-480x320.jpg",
        "https://media.onthemarket.com/properties/18927245/1598253333/image-3-480x320.jpg",
        "https://media.onthemarket.com/properties/18927245/1598253333/image-4-480x320.jpg"
      ],
      "sources": [
        {
          "portal": "OnTheMarket",
          "url": "https://www.onthemarket.com/details/18927245/"
        }
      ],
      "lat": 50.4307281,
      "lon": -3.6890014,
      "searchLocation": "Totnes",
      "searchLocations": [
        "Totnes"
      ],
      "autoRejected": true,
      "geoAccuracy": "address",
      "nearestAirport": {
        "name": "Exeter International Airport",
        "icao": "EGTE",
        "category": "airport",
        "usage": "commercial",
        "active": true,
        "distanceKm": 38.93828784340671,
        "distanceMiles": 24.195122855545474
      },
      "nearestAirstrip": {
        "name": "Marldon Airstrip",
        "icao": null,
        "category": "airstrip",
        "usage": "private",
        "active": false,
        "distanceKm": 6.6547270769573315,
        "distanceMiles": 4.135054418536054
      },
      "nearestHeliport": {
        "name": "Torquay Go-Kart circuit helipad",
        "icao": null,
        "category": "heliport",
        "usage": "private",
        "active": false,
        "distanceKm": 10.563098314748121,
        "distanceMiles": 6.563602962933355
      },
      "minAirportDistanceMiles": 4.135054418536054,
      "flyoverRef": {
        "location": "London Gatwick Area",
        "flightsPerDay": 688.1,
        "seasonalFlag": "stable",
        "generatedAt": "2026-06-26T12:59:20.862Z"
      },
      "keywordsMatched": 0,
      "baselineComparison": {
        "airportsCount": 0,
        "airstripsCount": 2,
        "helipadsCount": 2,
        "airportsDiff": -4,
        "airstripsDiff": 2,
        "helipadsDiff": -2,
        "flightsPerDay": 688.1,
        "flightsDiffPct": 715
      },
      "isNew": true,
      "retrievedAt": "2026-07-23T09:57:23.571Z"
    },
    {
      "title": "2 bedroom apartment for sale",
      "price": 130000,
      "address": "The Manor House (Totnes), Totnes TQ9",
      "bedrooms": 2,
      "bathrooms": null,
      "sqft": null,
      "postedDate": null,
      "agent": "Retirement Homesearch - South West of England",
      "agentPhone": "01425 292230",
      "type": "Apartment",
      "description": "",
      "images": [
        "https://media.onthemarket.com/properties/18610632/1623060967/image-0-480x320.jpg",
        "https://media.onthemarket.com/properties/18610632/1623060967/image-1-480x320.jpg",
        "https://media.onthemarket.com/properties/18610632/1623060967/image-2-480x320.jpg",
        "https://media.onthemarket.com/properties/18610632/1623060967/image-3-480x320.jpg",
        "https://media.onthemarket.com/properties/18610632/1623060967/image-4-480x320.jpg"
      ],
      "sources": [
        {
          "portal": "OnTheMarket",
          "url": "https://www.onthemarket.com/details/18610632/"
        }
      ],
      "lat": 50.41663565421549,
      "lon": -3.6912134759871997,
      "searchLocation": "Totnes",
      "searchLocations": [
        "Totnes"
      ],
      "autoRejected": false,
      "geoAccuracy": "postcode",
      "nearestAirport": {
        "name": "Exeter International Airport",
        "icao": "EGTE",
        "category": "airport",
        "usage": "commercial",
        "active": true,
        "distanceKm": 40.38102164109834,
        "distanceMiles": 25.09159579815092
      },
      "nearestAirstrip": {
        "name": "Halwell Airstrip",
        "icao": null,
        "category": "airstrip",
        "usage": "private",
        "active": false,
        "distanceKm": 5.828236845808926,
        "distanceMiles": 3.6214973571171383
      },
      "nearestHeliport": {
        "name": "Torquay Go-Kart circuit helipad",
        "icao": null,
        "category": "heliport",
        "usage": "private",
        "active": false,
        "distanceKm": 10.220867620855508,
        "distanceMiles": 6.350950734438608
      },
      "minAirportDistanceMiles": 3.6214973571171383,
      "flyoverRef": {
        "location": "London Gatwick Area",
        "flightsPerDay": 688.1,
        "seasonalFlag": "stable",
        "generatedAt": "2026-06-26T12:59:20.862Z"
      },
      "keywordsMatched": 0,
      "baselineComparison": {
        "airportsCount": 0,
        "airstripsCount": 2,
        "helipadsCount": 2,
        "airportsDiff": -4,
        "airstripsDiff": 2,
        "helipadsDiff": -2,
        "flightsPerDay": 688.1,
        "flightsDiffPct": 715
      },
      "isNew": true,
      "retrievedAt": "2026-07-23T09:57:23.571Z"
    },
    {
      "title": "2 bedroom cottage for sale",
      "price": 450000,
      "address": "Fore Street, Totnes",
      "bedrooms": 2,
      "bathrooms": null,
      "sqft": null,
      "postedDate": null,
      "agent": "Marchand Petit - Totnes",
      "agentPhone": "01803 268822",
      "type": "Cottage",
      "description": "",
      "images": [
        "https://media.onthemarket.com/properties/18129802/1589962027/image-0-480x320.jpg",
        "https://media.onthemarket.com/properties/18129802/1589962027/image-1-480x320.jpg",
        "https://media.onthemarket.com/properties/18129802/1589962027/image-2-480x320.jpg",
        "https://media.onthemarket.com/properties/18129802/1589962027/image-3-480x320.jpg",
        "https://media.onthemarket.com/properties/18129802/1589962027/image-4-480x320.jpg"
      ],
      "sources": [
        {
          "portal": "OnTheMarket",
          "url": "https://www.onthemarket.com/details/18129802/"
        }
      ],
      "lat": 50.4309997,
      "lon": -3.6841845,
      "searchLocation": "Totnes",
      "searchLocations": [
        "Totnes"
      ],
      "autoRejected": false,
      "geoAccuracy": "address",
      "nearestAirport": {
        "name": "Exeter International Airport",
        "icao": "EGTE",
        "category": "airport",
        "usage": "commercial",
        "active": true,
        "distanceKm": 38.743496982340794,
        "distanceMiles": 24.074085463414082
      },
      "nearestAirstrip": {
        "name": "Marldon Airstrip",
        "icao": null,
        "category": "airstrip",
        "usage": "private",
        "active": false,
        "distanceKm": 6.346539961564064,
        "distanceMiles": 3.943555882457024
      },
      "nearestHeliport": {
        "name": "Torquay Go-Kart circuit helipad",
        "icao": null,
        "category": "heliport",
        "usage": "private",
        "active": false,
        "distanceKm": 10.26058004731759,
        "distanceMiles": 6.375626884581779
      },
      "minAirportDistanceMiles": 3.943555882457024,
      "flyoverRef": {
        "location": "London Gatwick Area",
        "flightsPerDay": 688.1,
        "seasonalFlag": "stable",
        "generatedAt": "2026-06-26T12:59:20.862Z"
      },
      "keywordsMatched": 0,
      "baselineComparison": {
        "airportsCount": 0,
        "airstripsCount": 2,
        "helipadsCount": 2,
        "airportsDiff": -4,
        "airstripsDiff": 2,
        "helipadsDiff": -2,
        "flightsPerDay": 688.1,
        "flightsDiffPct": 715
      },
      "isNew": true,
      "retrievedAt": "2026-07-23T09:57:23.571Z"
    },
    {
      "title": "2 bedroom semi-detached house for sale",
      "price": 370000,
      "address": "South Street, Totnes",
      "bedrooms": 2,
      "bathrooms": null,
      "sqft": null,
      "postedDate": null,
      "agent": "Stags - Totnes",
      "agentPhone": "01803 268823",
      "type": "Semi-detached house",
      "description": "",
      "images": [
        "https://media.onthemarket.com/properties/17215756/1625910159/image-0-480x320.jpg",
        "https://media.onthemarket.com/properties/17215756/1625910159/image-1-480x320.jpg",
        "https://media.onthemarket.com/properties/17215756/1625910159/image-2-480x320.jpg",
        "https://media.onthemarket.com/properties/17215756/1625910159/image-3-480x320.jpg",
        "https://media.onthemarket.com/properties/17215756/1625910159/image-4-480x320.jpg"
      ],
      "sources": [
        {
          "portal": "OnTheMarket",
          "url": "https://www.onthemarket.com/details/17215756/"
        }
      ],
      "lat": 50.4307281,
      "lon": -3.6890014,
      "searchLocation": "Totnes",
      "searchLocations": [
        "Totnes"
      ],
      "autoRejected": true,
      "geoAccuracy": "address",
      "nearestAirport": {
        "name": "Exeter International Airport",
        "icao": "EGTE",
        "category": "airport",
        "usage": "commercial",
        "active": true,
        "distanceKm": 38.93828784340671,
        "distanceMiles": 24.195122855545474
      },
      "nearestAirstrip": {
        "name": "Marldon Airstrip",
        "icao": null,
        "category": "airstrip",
        "usage": "private",
        "active": false,
        "distanceKm": 6.6547270769573315,
        "distanceMiles": 4.135054418536054
      },
      "nearestHeliport": {
        "name": "Torquay Go-Kart circuit helipad",
        "icao": null,
        "category": "heliport",
        "usage": "private",
        "active": false,
        "distanceKm": 10.563098314748121,
        "distanceMiles": 6.563602962933355
      },
      "minAirportDistanceMiles": 4.135054418536054,
      "flyoverRef": {
        "location": "London Gatwick Area",
        "flightsPerDay": 688.1,
        "seasonalFlag": "stable",
        "generatedAt": "2026-06-26T12:59:20.862Z"
      },
      "keywordsMatched": 0,
      "baselineComparison": {
        "airportsCount": 0,
        "airstripsCount": 2,
        "helipadsCount": 2,
        "airportsDiff": -4,
        "airstripsDiff": 2,
        "helipadsDiff": -2,
        "flightsPerDay": 688.1,
        "flightsDiffPct": 715
      },
      "isNew": true,
      "retrievedAt": "2026-07-23T09:57:23.571Z"
    },
    {
      "title": "3 bedroom terraced house for sale",
      "price": 425000,
      "address": "Fore Street, Totnes TQ9",
      "bedrooms": 3,
      "bathrooms": null,
      "sqft": null,
      "postedDate": null,
      "agent": "Rendells - Totnes",
      "agentPhone": null,
      "type": "Terraced house",
      "description": "",
      "images": [
        "https://media.onthemarket.com/properties/19776259/1623549510/image-0-480x320.jpg",
        "https://media.onthemarket.com/properties/19776259/1623549510/image-1-480x320.jpg",
        "https://media.onthemarket.com/properties/19776259/1623549510/image-2-480x320.jpg",
        "https://media.onthemarket.com/properties/19776259/1623549510/image-3-480x320.jpg",
        "https://media.onthemarket.com/properties/19776259/1623549510/image-4-480x320.jpg"
      ],
      "sources": [
        {
          "portal": "OnTheMarket",
          "url": "https://www.onthemarket.com/details/19776259/"
        }
      ],
      "lat": 50.41663565421549,
      "lon": -3.6912134759871997,
      "searchLocation": "Totnes",
      "searchLocations": [
        "Totnes"
      ],
      "autoRejected": true,
      "geoAccuracy": "postcode",
      "nearestAirport": {
        "name": "Exeter International Airport",
        "icao": "EGTE",
        "category": "airport",
        "usage": "commercial",
        "active": true,
        "distanceKm": 40.38102164109834,
        "distanceMiles": 25.09159579815092
      },
      "nearestAirstrip": {
        "name": "Halwell Airstrip",
        "icao": null,
        "category": "airstrip",
        "usage": "private",
        "active": false,
        "distanceKm": 5.828236845808926,
        "distanceMiles": 3.6214973571171383
      },
      "nearestHeliport": {
        "name": "Torquay Go-Kart circuit helipad",
        "icao": null,
        "category": "heliport",
        "usage": "private",
        "active": false,
        "distanceKm": 10.220867620855508,
        "distanceMiles": 6.350950734438608
      },
      "minAirportDistanceMiles": 3.6214973571171383,
      "flyoverRef": {
        "location": "London Gatwick Area",
        "flightsPerDay": 688.1,
        "seasonalFlag": "stable",
        "generatedAt": "2026-06-26T12:59:20.862Z"
      },
      "keywordsMatched": 0,
      "baselineComparison": {
        "airportsCount": 0,
        "airstripsCount": 2,
        "helipadsCount": 2,
        "airportsDiff": -4,
        "airstripsDiff": 2,
        "helipadsDiff": -2,
        "flightsPerDay": 688.1,
        "flightsDiffPct": 715
      },
      "isNew": true,
      "retrievedAt": "2026-07-23T09:57:23.571Z"
    },
    {
      "title": "3 bedroom apartment for sale",
      "price": 350000,
      "address": "High Street, Totnes TQ9",
      "bedrooms": 3,
      "bathrooms": null,
      "sqft": null,
      "postedDate": null,
      "agent": "Rendells - Totnes",
      "agentPhone": null,
      "type": "Apartment",
      "description": "",
      "images": [
        "https://media.onthemarket.com/properties/14921166/1612250532/image-0-480x320.jpg",
        "https://media.onthemarket.com/properties/14921166/1619602155/image-1-480x320.jpg",
        "https://media.onthemarket.com/properties/14921166/1619602155/image-2-480x320.jpg",
        "https://media.onthemarket.com/properties/14921166/1619602155/image-3-480x320.jpg",
        "https://media.onthemarket.com/properties/14921166/1619602155/image-4-480x320.jpg"
      ],
      "sources": [
        {
          "portal": "OnTheMarket",
          "url": "https://www.onthemarket.com/details/14921166/"
        }
      ],
      "lat": 50.41663565421549,
      "lon": -3.6912134759871997,
      "searchLocation": "Totnes",
      "searchLocations": [
        "Totnes"
      ],
      "autoRejected": false,
      "geoAccuracy": "postcode",
      "nearestAirport": {
        "name": "Exeter International Airport",
        "icao": "EGTE",
        "category": "airport",
        "usage": "commercial",
        "active": true,
        "distanceKm": 40.38102164109834,
        "distanceMiles": 25.09159579815092
      },
      "nearestAirstrip": {
        "name": "Halwell Airstrip",
        "icao": null,
        "category": "airstrip",
        "usage": "private",
        "active": false,
        "distanceKm": 5.828236845808926,
        "distanceMiles": 3.6214973571171383
      },
      "nearestHeliport": {
        "name": "Torquay Go-Kart circuit helipad",
        "icao": null,
        "category": "heliport",
        "usage": "private",
        "active": false,
        "distanceKm": 10.220867620855508,
        "distanceMiles": 6.350950734438608
      },
      "minAirportDistanceMiles": 3.6214973571171383,
      "flyoverRef": {
        "location": "London Gatwick Area",
        "flightsPerDay": 688.1,
        "seasonalFlag": "stable",
        "generatedAt": "2026-06-26T12:59:20.862Z"
      },
      "keywordsMatched": 0,
      "baselineComparison": {
        "airportsCount": 0,
        "airstripsCount": 2,
        "helipadsCount": 2,
        "airportsDiff": -4,
        "airstripsDiff": 2,
        "helipadsDiff": -2,
        "flightsPerDay": 688.1,
        "flightsDiffPct": 715
      },
      "isNew": true,
      "retrievedAt": "2026-07-23T09:57:23.571Z"
    },
    {
      "title": "2 bedroom terraced house for sale",
      "price": 3250003,
      "address": "3 Bank Lane, Totnes TQ9",
      "bedrooms": 2,
      "bathrooms": null,
      "sqft": null,
      "postedDate": null,
      "agent": "Rendells - Totnes",
      "agentPhone": null,
      "type": "Terraced house",
      "description": "",
      "images": [
        "https://media.onthemarket.com/properties/14344704/1630179603/image-0-480x320.jpg",
        "https://media.onthemarket.com/properties/14344704/1630179603/image-1-480x320.jpg",
        "https://media.onthemarket.com/properties/14344704/1630179603/image-2-480x320.jpg",
        "https://media.onthemarket.com/properties/14344704/1630179603/image-3-480x320.jpg",
        "https://media.onthemarket.com/properties/14344704/1630179603/image-4-480x320.jpg"
      ],
      "sources": [
        {
          "portal": "OnTheMarket",
          "url": "https://www.onthemarket.com/details/14344704/"
        }
      ],
      "lat": 50.41663565421549,
      "lon": -3.6912134759871997,
      "searchLocation": "Totnes",
      "searchLocations": [
        "Totnes"
      ],
      "autoRejected": true,
      "geoAccuracy": "postcode",
      "nearestAirport": {
        "name": "Exeter International Airport",
        "icao": "EGTE",
        "category": "airport",
        "usage": "commercial",
        "active": true,
        "distanceKm": 40.38102164109834,
        "distanceMiles": 25.09159579815092
      },
      "nearestAirstrip": {
        "name": "Halwell Airstrip",
        "icao": null,
        "category": "airstrip",
        "usage": "private",
        "active": false,
        "distanceKm": 5.828236845808926,
        "distanceMiles": 3.6214973571171383
      },
      "nearestHeliport": {
        "name": "Torquay Go-Kart circuit helipad",
        "icao": null,
        "category": "heliport",
        "usage": "private",
        "active": false,
        "distanceKm": 10.220867620855508,
        "distanceMiles": 6.350950734438608
      },
      "minAirportDistanceMiles": 3.6214973571171383,
      "flyoverRef": {
        "location": "London Gatwick Area",
        "flightsPerDay": 688.1,
        "seasonalFlag": "stable",
        "generatedAt": "2026-06-26T12:59:20.862Z"
      },
      "keywordsMatched": 0,
      "baselineComparison": {
        "airportsCount": 0,
        "airstripsCount": 2,
        "helipadsCount": 2,
        "airportsDiff": -4,
        "airstripsDiff": 2,
        "helipadsDiff": -2,
        "flightsPerDay": 688.1,
        "flightsDiffPct": 715
      },
      "isNew": true,
      "retrievedAt": "2026-07-23T09:57:23.571Z"
    },
    {
      "title": "2 bedroom apartment for sale",
      "price": 95000,
      "address": "Coronation Road, Totnes TQ9",
      "bedrooms": 2,
      "bathrooms": null,
      "sqft": null,
      "postedDate": null,
      "agent": "Rendells - Totnes",
      "agentPhone": null,
      "type": "Apartment",
      "description": "A first-floor light and airy retirement apartmentOpen living/dining roomRetirementRendells - TotnesAdded > 14 days",
      "images": [
        "https://media.onthemarket.com/properties/15977763/1612250527/image-0-480x320.jpg",
        "https://media.onthemarket.com/properties/15977763/1619602133/image-1-480x320.jpg",
        "https://media.onthemarket.com/properties/15977763/1619602133/image-2-480x320.jpg",
        "https://media.onthemarket.com/properties/15977763/1619602133/image-3-480x320.jpg",
        "https://media.onthemarket.com/properties/15977763/1619602133/image-4-480x320.jpg"
      ],
      "sources": [
        {
          "portal": "OnTheMarket",
          "url": "https://www.onthemarket.com/details/15977763/"
        }
      ],
      "lat": 50.41663565421549,
      "lon": -3.6912134759871997,
      "searchLocation": "Totnes",
      "searchLocations": [
        "Totnes"
      ],
      "autoRejected": false,
      "geoAccuracy": "postcode",
      "nearestAirport": {
        "name": "Exeter International Airport",
        "icao": "EGTE",
        "category": "airport",
        "usage": "commercial",
        "active": true,
        "distanceKm": 40.38102164109834,
        "distanceMiles": 25.09159579815092
      },
      "nearestAirstrip": {
        "name": "Halwell Airstrip",
        "icao": null,
        "category": "airstrip",
        "usage": "private",
        "active": false,
        "distanceKm": 5.828236845808926,
        "distanceMiles": 3.6214973571171383
      },
      "nearestHeliport": {
        "name": "Torquay Go-Kart circuit helipad",
        "icao": null,
        "category": "heliport",
        "usage": "private",
        "active": false,
        "distanceKm": 10.220867620855508,
        "distanceMiles": 6.350950734438608
      },
      "minAirportDistanceMiles": 3.6214973571171383,
      "flyoverRef": {
        "location": "London Gatwick Area",
        "flightsPerDay": 688.1,
        "seasonalFlag": "stable",
        "generatedAt": "2026-06-26T12:59:20.862Z"
      },
      "keywordsMatched": 0,
      "baselineComparison": {
        "airportsCount": 0,
        "airstripsCount": 2,
        "helipadsCount": 2,
        "airportsDiff": -4,
        "airstripsDiff": 2,
        "helipadsDiff": -2,
        "flightsPerDay": 688.1,
        "flightsDiffPct": 715
      },
      "isNew": true,
      "retrievedAt": "2026-07-23T09:57:23.571Z"
    },
    {
      "title": "2 bed property for sale",
      "price": 315000,
      "address": "Fore Street, Totnes TQ9",
      "bedrooms": 2,
      "bathrooms": 1,
      "sqft": null,
      "type": "Property",
      "description": "a stone’s throw from the vibrant, historic heart of Totnes High Street, this stunning first-floor apartment ...Listed on 23rd Jun 2026",
      "postedDate": null,
      "agent": null,
      "agentPhone": null,
      "images": [
        "https://lid.zoocdn.com/645/430/75431765257fef410f2a94012439f006757a3631.jpg"
      ],
      "sources": [
        {
          "portal": "Zoopla",
          "url": "https://www.zoopla.co.uk/for-sale/details/73522440/"
        }
      ],
      "lat": 50.41663565421549,
      "lon": -3.6912134759871997,
      "searchLocation": "Totnes",
      "searchLocations": [
        "Totnes"
      ],
      "autoRejected": false,
      "geoAccuracy": "postcode",
      "nearestAirport": {
        "name": "Exeter International Airport",
        "icao": "EGTE",
        "category": "airport",
        "usage": "commercial",
        "active": true,
        "distanceKm": 40.38102164109834,
        "distanceMiles": 25.09159579815092
      },
      "nearestAirstrip": {
        "name": "Halwell Airstrip",
        "icao": null,
        "category": "airstrip",
        "usage": "private",
        "active": false,
        "distanceKm": 5.828236845808926,
        "distanceMiles": 3.6214973571171383
      },
      "nearestHeliport": {
        "name": "Torquay Go-Kart circuit helipad",
        "icao": null,
        "category": "heliport",
        "usage": "private",
        "active": false,
        "distanceKm": 10.220867620855508,
        "distanceMiles": 6.350950734438608
      },
      "minAirportDistanceMiles": 3.6214973571171383,
      "flyoverRef": {
        "location": "London Gatwick Area",
        "flightsPerDay": 688.1,
        "seasonalFlag": "stable",
        "generatedAt": "2026-06-26T12:59:20.862Z"
      },
      "keywordsMatched": 0,
      "baselineComparison": {
        "airportsCount": 0,
        "airstripsCount": 2,
        "helipadsCount": 2,
        "airportsDiff": -4,
        "airstripsDiff": 2,
        "helipadsDiff": -2,
        "flightsPerDay": 688.1,
        "flightsDiffPct": 715
      },
      "isNew": true,
      "retrievedAt": "2026-07-23T09:57:23.571Z"
    },
    {
      "title": "2 bed property for sale",
      "price": 130000,
      "address": "The Manor House (Totnes), Totnes TQ9",
      "bedrooms": 2,
      "bathrooms": 1,
      "sqft": null,
      "type": "Property",
      "description": "A two bedroom ground floor retirement apartment The Manor House retirement apartments have been constructed around the ...Listed on 29th Jan 2026Retirement",
      "postedDate": null,
      "agent": null,
      "agentPhone": null,
      "images": [
        "https://lid.zoocdn.com/645/430/b61013c6ddcd33cdb59edd8d8e176d52e1f383a8.jpg"
      ],
      "sources": [
        {
          "portal": "Zoopla",
          "url": "https://www.zoopla.co.uk/for-sale/details/72303956/"
        }
      ],
      "lat": 50.41663565421549,
      "lon": -3.6912134759871997,
      "searchLocation": "Totnes",
      "searchLocations": [
        "Totnes"
      ],
      "autoRejected": false,
      "geoAccuracy": "postcode",
      "nearestAirport": {
        "name": "Exeter International Airport",
        "icao": "EGTE",
        "category": "airport",
        "usage": "commercial",
        "active": true,
        "distanceKm": 40.38102164109834,
        "distanceMiles": 25.09159579815092
      },
      "nearestAirstrip": {
        "name": "Halwell Airstrip",
        "icao": null,
        "category": "airstrip",
        "usage": "private",
        "active": false,
        "distanceKm": 5.828236845808926,
        "distanceMiles": 3.6214973571171383
      },
      "nearestHeliport": {
        "name": "Torquay Go-Kart circuit helipad",
        "icao": null,
        "category": "heliport",
        "usage": "private",
        "active": false,
        "distanceKm": 10.220867620855508,
        "distanceMiles": 6.350950734438608
      },
      "minAirportDistanceMiles": 3.6214973571171383,
      "flyoverRef": {
        "location": "London Gatwick Area",
        "flightsPerDay": 688.1,
        "seasonalFlag": "stable",
        "generatedAt": "2026-06-26T12:59:20.862Z"
      },
      "keywordsMatched": 0,
      "baselineComparison": {
        "airportsCount": 0,
        "airstripsCount": 2,
        "helipadsCount": 2,
        "airportsDiff": -4,
        "airstripsDiff": 2,
        "helipadsDiff": -2,
        "flightsPerDay": 688.1,
        "flightsDiffPct": 715
      },
      "isNew": true,
      "retrievedAt": "2026-07-23T09:57:23.571Z"
    },
    {
      "title": "2 bed property for sale",
      "price": 135000,
      "address": "Coronation Road, Totnes TQ9",
      "bedrooms": 2,
      "bathrooms": 1,
      "sqft": null,
      "type": "Property",
      "description": "",
      "postedDate": "Reduced",
      "agent": null,
      "agentPhone": null,
      "images": [
        "https://lid.zoocdn.com/645/430/904d2b44471a911eae1fe48f3685a68e40419dc3.jpg"
      ],
      "sources": [
        {
          "portal": "Zoopla",
          "url": "https://www.zoopla.co.uk/for-sale/details/66103877/"
        }
      ],
      "lat": 50.41663565421549,
      "lon": -3.6912134759871997,
      "searchLocation": "Totnes",
      "searchLocations": [
        "Totnes"
      ],
      "autoRejected": false,
      "geoAccuracy": "postcode",
      "nearestAirport": {
        "name": "Exeter International Airport",
        "icao": "EGTE",
        "category": "airport",
        "usage": "commercial",
        "active": true,
        "distanceKm": 40.38102164109834,
        "distanceMiles": 25.09159579815092
      },
      "nearestAirstrip": {
        "name": "Halwell Airstrip",
        "icao": null,
        "category": "airstrip",
        "usage": "private",
        "active": false,
        "distanceKm": 5.828236845808926,
        "distanceMiles": 3.6214973571171383
      },
      "nearestHeliport": {
        "name": "Torquay Go-Kart circuit helipad",
        "icao": null,
        "category": "heliport",
        "usage": "private",
        "active": false,
        "distanceKm": 10.220867620855508,
        "distanceMiles": 6.350950734438608
      },
      "minAirportDistanceMiles": 3.6214973571171383,
      "flyoverRef": {
        "location": "London Gatwick Area",
        "flightsPerDay": 688.1,
        "seasonalFlag": "stable",
        "generatedAt": "2026-06-26T12:59:20.862Z"
      },
      "keywordsMatched": 0,
      "baselineComparison": {
        "airportsCount": 0,
        "airstripsCount": 2,
        "helipadsCount": 2,
        "airportsDiff": -4,
        "airstripsDiff": 2,
        "helipadsDiff": -2,
        "flightsPerDay": 688.1,
        "flightsDiffPct": 715
      },
      "isNew": true,
      "retrievedAt": "2026-07-23T09:57:23.571Z"
    },
    {
      "title": "2 bed property for sale",
      "price": 375000,
      "address": "South Street, Totnes, Devon. TQ9",
      "bedrooms": 2,
      "bathrooms": 1,
      "sqft": null,
      "type": "Property",
      "description": "A converted Barn that comprises open plan accommodation situated in the heart of Totnes with parking facility. The property ...Listed on 3rd Mar 2026",
      "postedDate": "Reduced",
      "agent": null,
      "agentPhone": null,
      "images": [
        "https://lid.zoocdn.com/645/430/2384f417b655229b62f27e9b6a195f71e185d3ef.jpg"
      ],
      "sources": [
        {
          "portal": "Zoopla",
          "url": "https://www.zoopla.co.uk/for-sale/details/72568819/"
        }
      ],
      "lat": 50.41663565421549,
      "lon": -3.6912134759871997,
      "searchLocation": "Totnes",
      "searchLocations": [
        "Totnes"
      ],
      "autoRejected": false,
      "geoAccuracy": "postcode",
      "nearestAirport": {
        "name": "Exeter International Airport",
        "icao": "EGTE",
        "category": "airport",
        "usage": "commercial",
        "active": true,
        "distanceKm": 40.38102164109834,
        "distanceMiles": 25.09159579815092
      },
      "nearestAirstrip": {
        "name": "Halwell Airstrip",
        "icao": null,
        "category": "airstrip",
        "usage": "private",
        "active": false,
        "distanceKm": 5.828236845808926,
        "distanceMiles": 3.6214973571171383
      },
      "nearestHeliport": {
        "name": "Torquay Go-Kart circuit helipad",
        "icao": null,
        "category": "heliport",
        "usage": "private",
        "active": false,
        "distanceKm": 10.220867620855508,
        "distanceMiles": 6.350950734438608
      },
      "minAirportDistanceMiles": 3.6214973571171383,
      "flyoverRef": {
        "location": "London Gatwick Area",
        "flightsPerDay": 688.1,
        "seasonalFlag": "stable",
        "generatedAt": "2026-06-26T12:59:20.862Z"
      },
      "keywordsMatched": 0,
      "baselineComparison": {
        "airportsCount": 0,
        "airstripsCount": 2,
        "helipadsCount": 2,
        "airportsDiff": -4,
        "airstripsDiff": 2,
        "helipadsDiff": -2,
        "flightsPerDay": 688.1,
        "flightsDiffPct": 715
      },
      "isNew": true,
      "retrievedAt": "2026-07-23T09:57:23.571Z"
    },
    {
      "title": "2 bed flat for sale",
      "price": 270000,
      "address": "Ticklemore Street, Totnes TQ9",
      "bedrooms": 2,
      "bathrooms": 1,
      "sqft": null,
      "type": "Flat",
      "description": "",
      "postedDate": null,
      "agent": null,
      "agentPhone": null,
      "images": [
        "https://lid.zoocdn.com/645/430/edaec9018076d08acf74bab010ef92cdcab2c798.jpg"
      ],
      "sources": [
        {
          "portal": "Zoopla",
          "url": "https://www.zoopla.co.uk/for-sale/details/73604370/"
        }
      ],
      "lat": 50.41663565421549,
      "lon": -3.6912134759871997,
      "searchLocation": "Totnes",
      "searchLocations": [
        "Totnes"
      ],
      "autoRejected": false,
      "geoAccuracy": "postcode",
      "nearestAirport": {
        "name": "Exeter International Airport",
        "icao": "EGTE",
        "category": "airport",
        "usage": "commercial",
        "active": true,
        "distanceKm": 40.38102164109834,
        "distanceMiles": 25.09159579815092
      },
      "nearestAirstrip": {
        "name": "Halwell Airstrip",
        "icao": null,
        "category": "airstrip",
        "usage": "private",
        "active": false,
        "distanceKm": 5.828236845808926,
        "distanceMiles": 3.6214973571171383
      },
      "nearestHeliport": {
        "name": "Torquay Go-Kart circuit helipad",
        "icao": null,
        "category": "heliport",
        "usage": "private",
        "active": false,
        "distanceKm": 10.220867620855508,
        "distanceMiles": 6.350950734438608
      },
      "minAirportDistanceMiles": 3.6214973571171383,
      "flyoverRef": {
        "location": "London Gatwick Area",
        "flightsPerDay": 688.1,
        "seasonalFlag": "stable",
        "generatedAt": "2026-06-26T12:59:20.862Z"
      },
      "keywordsMatched": 0,
      "baselineComparison": {
        "airportsCount": 0,
        "airstripsCount": 2,
        "helipadsCount": 2,
        "airportsDiff": -4,
        "airstripsDiff": 2,
        "helipadsDiff": -2,
        "flightsPerDay": 688.1,
        "flightsDiffPct": 715
      },
      "isNew": true,
      "retrievedAt": "2026-07-23T09:57:23.571Z"
    },
    {
      "title": "2 bed flat for sale",
      "price": 170000,
      "address": "t. Katherines Mews, St. Katherines Way, Totnes, Devon TQ9",
      "bedrooms": 2,
      "bathrooms": 1,
      "sqft": null,
      "type": "flat",
      "description": "this charming two-bedroom flat offers ...Listed on 25th Oct 2025",
      "postedDate": null,
      "agent": null,
      "agentPhone": null,
      "images": [
        "https://lid.zoocdn.com/645/430/9e1973189fc3562a474a5b584ccc5cb868059429.jpg"
      ],
      "sources": [
        {
          "portal": "Zoopla",
          "url": "https://www.zoopla.co.uk/for-sale/details/71651175/"
        }
      ],
      "lat": 50.41663565421549,
      "lon": -3.6912134759871997,
      "searchLocation": "Totnes",
      "searchLocations": [
        "Totnes"
      ],
      "autoRejected": false,
      "geoAccuracy": "postcode",
      "nearestAirport": {
        "name": "Exeter International Airport",
        "icao": "EGTE",
        "category": "airport",
        "usage": "commercial",
        "active": true,
        "distanceKm": 40.38102164109834,
        "distanceMiles": 25.09159579815092
      },
      "nearestAirstrip": {
        "name": "Halwell Airstrip",
        "icao": null,
        "category": "airstrip",
        "usage": "private",
        "active": false,
        "distanceKm": 5.828236845808926,
        "distanceMiles": 3.6214973571171383
      },
      "nearestHeliport": {
        "name": "Torquay Go-Kart circuit helipad",
        "icao": null,
        "category": "heliport",
        "usage": "private",
        "active": false,
        "distanceKm": 10.220867620855508,
        "distanceMiles": 6.350950734438608
      },
      "minAirportDistanceMiles": 3.6214973571171383,
      "flyoverRef": {
        "location": "London Gatwick Area",
        "flightsPerDay": 688.1,
        "seasonalFlag": "stable",
        "generatedAt": "2026-06-26T12:59:20.862Z"
      },
      "keywordsMatched": 0,
      "baselineComparison": {
        "airportsCount": 0,
        "airstripsCount": 2,
        "helipadsCount": 2,
        "airportsDiff": -4,
        "airstripsDiff": 2,
        "helipadsDiff": -2,
        "flightsPerDay": 688.1,
        "flightsDiffPct": 715
      },
      "isNew": true,
      "retrievedAt": "2026-07-23T09:57:23.571Z"
    },
    {
      "title": "3 bed property for sale",
      "price": 285000,
      "address": "High Street, Totnes TQ9",
      "bedrooms": 3,
      "bathrooms": 1,
      "sqft": null,
      "type": "Property",
      "description": "",
      "postedDate": null,
      "agent": null,
      "agentPhone": null,
      "images": [
        "https://lid.zoocdn.com/645/430/faa5c83b5e448ee3f907a78f9720eaf8c7a15790.jpg"
      ],
      "sources": [
        {
          "portal": "Zoopla",
          "url": "https://www.zoopla.co.uk/for-sale/details/73401838/"
        }
      ],
      "lat": 50.41663565421549,
      "lon": -3.6912134759871997,
      "searchLocation": "Totnes",
      "searchLocations": [
        "Totnes"
      ],
      "autoRejected": false,
      "geoAccuracy": "postcode",
      "nearestAirport": {
        "name": "Exeter International Airport",
        "icao": "EGTE",
        "category": "airport",
        "usage": "commercial",
        "active": true,
        "distanceKm": 40.38102164109834,
        "distanceMiles": 25.09159579815092
      },
      "nearestAirstrip": {
        "name": "Halwell Airstrip",
        "icao": null,
        "category": "airstrip",
        "usage": "private",
        "active": false,
        "distanceKm": 5.828236845808926,
        "distanceMiles": 3.6214973571171383
      },
      "nearestHeliport": {
        "name": "Torquay Go-Kart circuit helipad",
        "icao": null,
        "category": "heliport",
        "usage": "private",
        "active": false,
        "distanceKm": 10.220867620855508,
        "distanceMiles": 6.350950734438608
      },
      "minAirportDistanceMiles": 3.6214973571171383,
      "flyoverRef": {
        "location": "London Gatwick Area",
        "flightsPerDay": 688.1,
        "seasonalFlag": "stable",
        "generatedAt": "2026-06-26T12:59:20.862Z"
      },
      "keywordsMatched": 0,
      "baselineComparison": {
        "airportsCount": 0,
        "airstripsCount": 2,
        "helipadsCount": 2,
        "airportsDiff": -4,
        "airstripsDiff": 2,
        "helipadsDiff": -2,
        "flightsPerDay": 688.1,
        "flightsDiffPct": 715
      },
      "isNew": true,
      "retrievedAt": "2026-07-23T09:57:23.571Z"
    },
    {
      "title": "2 bed property for sale",
      "price": 225000,
      "address": "Rotherfold, Totnes TQ9",
      "bedrooms": 2,
      "bathrooms": 1,
      "sqft": null,
      "type": "Property",
      "description": "",
      "postedDate": "Reduced",
      "agent": null,
      "agentPhone": null,
      "images": [
        "https://lid.zoocdn.com/645/430/bbe8ffa4b2277cf1241d3081e56e9343661285fb.jpg"
      ],
      "sources": [
        {
          "portal": "Zoopla",
          "url": "https://www.zoopla.co.uk/for-sale/details/73167470/"
        }
      ],
      "lat": 50.41663565421549,
      "lon": -3.6912134759871997,
      "searchLocation": "Totnes",
      "searchLocations": [
        "Totnes"
      ],
      "autoRejected": false,
      "geoAccuracy": "postcode",
      "nearestAirport": {
        "name": "Exeter International Airport",
        "icao": "EGTE",
        "category": "airport",
        "usage": "commercial",
        "active": true,
        "distanceKm": 40.38102164109834,
        "distanceMiles": 25.09159579815092
      },
      "nearestAirstrip": {
        "name": "Halwell Airstrip",
        "icao": null,
        "category": "airstrip",
        "usage": "private",
        "active": false,
        "distanceKm": 5.828236845808926,
        "distanceMiles": 3.6214973571171383
      },
      "nearestHeliport": {
        "name": "Torquay Go-Kart circuit helipad",
        "icao": null,
        "category": "heliport",
        "usage": "private",
        "active": false,
        "distanceKm": 10.220867620855508,
        "distanceMiles": 6.350950734438608
      },
      "minAirportDistanceMiles": 3.6214973571171383,
      "flyoverRef": {
        "location": "London Gatwick Area",
        "flightsPerDay": 688.1,
        "seasonalFlag": "stable",
        "generatedAt": "2026-06-26T12:59:20.862Z"
      },
      "keywordsMatched": 0,
      "baselineComparison": {
        "airportsCount": 0,
        "airstripsCount": 2,
        "helipadsCount": 2,
        "airportsDiff": -4,
        "airstripsDiff": 2,
        "helipadsDiff": -2,
        "flightsPerDay": 688.1,
        "flightsDiffPct": 715
      },
      "isNew": true,
      "retrievedAt": "2026-07-23T09:57:23.571Z"
    },
    {
      "title": "3 bed end of terrace house for sale",
      "price": 300000,
      "address": "Warland, Totnes, Devon TQ9",
      "bedrooms": 3,
      "bathrooms": 1,
      "sqft": null,
      "type": "end of terrace house",
      "description": "this charming 3 - bedroom end of terrace house in the sought after area of The Warlands, Totnes. Spread across three ...Listed on 30th Jul 2024",
      "postedDate": "Reduced",
      "agent": null,
      "agentPhone": null,
      "images": [
        "https://lid.zoocdn.com/645/430/be78381c6cfc16fc4a790b90a26f3954ff37c4b8.jpg"
      ],
      "sources": [
        {
          "portal": "Zoopla",
          "url": "https://www.zoopla.co.uk/for-sale/details/67955882/"
        }
      ],
      "lat": 50.41663565421549,
      "lon": -3.6912134759871997,
      "searchLocation": "Totnes",
      "searchLocations": [
        "Totnes"
      ],
      "autoRejected": true,
      "geoAccuracy": "postcode",
      "nearestAirport": {
        "name": "Exeter International Airport",
        "icao": "EGTE",
        "category": "airport",
        "usage": "commercial",
        "active": true,
        "distanceKm": 40.38102164109834,
        "distanceMiles": 25.09159579815092
      },
      "nearestAirstrip": {
        "name": "Halwell Airstrip",
        "icao": null,
        "category": "airstrip",
        "usage": "private",
        "active": false,
        "distanceKm": 5.828236845808926,
        "distanceMiles": 3.6214973571171383
      },
      "nearestHeliport": {
        "name": "Torquay Go-Kart circuit helipad",
        "icao": null,
        "category": "heliport",
        "usage": "private",
        "active": false,
        "distanceKm": 10.220867620855508,
        "distanceMiles": 6.350950734438608
      },
      "minAirportDistanceMiles": 3.6214973571171383,
      "flyoverRef": {
        "location": "London Gatwick Area",
        "flightsPerDay": 688.1,
        "seasonalFlag": "stable",
        "generatedAt": "2026-06-26T12:59:20.862Z"
      },
      "keywordsMatched": 0,
      "baselineComparison": {
        "airportsCount": 0,
        "airstripsCount": 2,
        "helipadsCount": 2,
        "airportsDiff": -4,
        "airstripsDiff": 2,
        "helipadsDiff": -2,
        "flightsPerDay": 688.1,
        "flightsDiffPct": 715
      },
      "isNew": true,
      "retrievedAt": "2026-07-23T09:57:23.571Z"
    },
    {
      "title": "3 bed property for sale",
      "price": 130000,
      "address": "Plymouth Road, Totnes TQ9",
      "bedrooms": 3,
      "bathrooms": 1,
      "sqft": null,
      "type": "Property",
      "description": "",
      "postedDate": "Reduced",
      "agent": null,
      "agentPhone": null,
      "images": [
        "https://lid.zoocdn.com/645/430/26b60e5c81e8164c77d91d07b4306d9cc8413e36.jpg"
      ],
      "sources": [
        {
          "portal": "Zoopla",
          "url": "https://www.zoopla.co.uk/for-sale/details/73667974/"
        }
      ],
      "lat": 50.41663565421549,
      "lon": -3.6912134759871997,
      "searchLocation": "Totnes",
      "searchLocations": [
        "Totnes"
      ],
      "autoRejected": false,
      "geoAccuracy": "postcode",
      "nearestAirport": {
        "name": "Exeter International Airport",
        "icao": "EGTE",
        "category": "airport",
        "usage": "commercial",
        "active": true,
        "distanceKm": 40.38102164109834,
        "distanceMiles": 25.09159579815092
      },
      "nearestAirstrip": {
        "name": "Halwell Airstrip",
        "icao": null,
        "category": "airstrip",
        "usage": "private",
        "active": false,
        "distanceKm": 5.828236845808926,
        "distanceMiles": 3.6214973571171383
      },
      "nearestHeliport": {
        "name": "Torquay Go-Kart circuit helipad",
        "icao": null,
        "category": "heliport",
        "usage": "private",
        "active": false,
        "distanceKm": 10.220867620855508,
        "distanceMiles": 6.350950734438608
      },
      "minAirportDistanceMiles": 3.6214973571171383,
      "flyoverRef": {
        "location": "London Gatwick Area",
        "flightsPerDay": 688.1,
        "seasonalFlag": "stable",
        "generatedAt": "2026-06-26T12:59:20.862Z"
      },
      "keywordsMatched": 0,
      "baselineComparison": {
        "airportsCount": 0,
        "airstripsCount": 2,
        "helipadsCount": 2,
        "airportsDiff": -4,
        "airstripsDiff": 2,
        "helipadsDiff": -2,
        "flightsPerDay": 688.1,
        "flightsDiffPct": 715
      },
      "isNew": true,
      "retrievedAt": "2026-07-23T09:57:23.571Z"
    },
    {
      "title": "2 bed property for sale",
      "price": 440000,
      "address": "Moat Hill, Totnes TQ9",
      "bedrooms": 2,
      "bathrooms": 2,
      "sqft": null,
      "type": "Property",
      "description": "with Views and GardenListed on 27th Feb 2026",
      "postedDate": null,
      "agent": null,
      "agentPhone": null,
      "images": [
        "https://lid.zoocdn.com/645/430/382fb2eb5d1781a84fa85a172553687370434fb0.jpg",
        "https://lid.zoocdn.com/645/430/993f5b94b447a8f686ea5615169d07192d979d4c.jpg",
        "https://lid.zoocdn.com/645/430/1ff1667f782ff5e4c682e673a08ddbd495b645e7.jpg",
        "https://lid.zoocdn.com/645/430/dc2e964247a3e7d9737cb6596fdcde34875a8155.jpg",
        "https://lid.zoocdn.com/645/430/b1efaa84cb9f9bd605cb29850aadc378befe4ad8.jpg",
        "https://lid.zoocdn.com/645/430/4ed8ced99c98653346cd2606bacdf980447c012b.jpg",
        "https://lid.zoocdn.com/645/430/cc4f72d97b539d288f65563b4a04293eddca6ac6.jpg",
        "https://lid.zoocdn.com/645/430/8a983d1ccf6dde8a450c65e963aabb87418dcda7.jpg",
        "https://lid.zoocdn.com/645/430/d38b094dd061214f14dd7f2cfb105933ef72ae1b.jpg",
        "https://lid.zoocdn.com/645/430/8483b061ea5741cbe6d7b53faace6d813329b50f.jpg",
        "https://lid.zoocdn.com/645/430/2504902a3ee5c041cd410eb0006a54778a3f5ab5.jpg",
        "https://lid.zoocdn.com/645/430/c1345c973f3ddcbfd9fd165dea9a6fc8398084bd.jpg",
        "https://lid.zoocdn.com/645/430/443f018f54d596dedf1f33d51fc336c07ec906fc.jpg",
        "https://lid.zoocdn.com/645/430/d27c83fc3a877a7558139a3f21ca39076a5d902c.jpg",
        "https://lid.zoocdn.com/645/430/4dd873720ead2e6d342d84f9e101e0db5f0e5c81.jpg"
      ],
      "sources": [
        {
          "portal": "Zoopla",
          "url": "https://www.zoopla.co.uk/for-sale/details/72541029/"
        }
      ],
      "lat": 50.41663565421549,
      "lon": -3.6912134759871997,
      "searchLocation": "Totnes",
      "searchLocations": [
        "Totnes"
      ],
      "autoRejected": false,
      "geoAccuracy": "postcode",
      "nearestAirport": {
        "name": "Exeter International Airport",
        "icao": "EGTE",
        "category": "airport",
        "usage": "commercial",
        "active": true,
        "distanceKm": 40.38102164109834,
        "distanceMiles": 25.09159579815092
      },
      "nearestAirstrip": {
        "name": "Halwell Airstrip",
        "icao": null,
        "category": "airstrip",
        "usage": "private",
        "active": false,
        "distanceKm": 5.828236845808926,
        "distanceMiles": 3.6214973571171383
      },
      "nearestHeliport": {
        "name": "Torquay Go-Kart circuit helipad",
        "icao": null,
        "category": "heliport",
        "usage": "private",
        "active": false,
        "distanceKm": 10.220867620855508,
        "distanceMiles": 6.350950734438608
      },
      "minAirportDistanceMiles": 3.6214973571171383,
      "flyoverRef": {
        "location": "London Gatwick Area",
        "flightsPerDay": 688.1,
        "seasonalFlag": "stable",
        "generatedAt": "2026-06-26T12:59:20.862Z"
      },
      "keywordsMatched": 1,
      "baselineComparison": {
        "airportsCount": 0,
        "airstripsCount": 2,
        "helipadsCount": 2,
        "airportsDiff": -4,
        "airstripsDiff": 2,
        "helipadsDiff": -2,
        "flightsPerDay": 688.1,
        "flightsDiffPct": 715
      },
      "isNew": true,
      "retrievedAt": "2026-07-23T09:57:23.571Z"
    },
    {
      "title": "2 bed property for sale",
      "price": 350000,
      "address": "Dart Villas, Totnes TQ9",
      "bedrooms": 2,
      "bathrooms": 1,
      "sqft": null,
      "type": "Property",
      "description": "this Lovely 2 Bedroom Apartment with ParkingListed on 12th Mar 2026",
      "postedDate": null,
      "agent": null,
      "agentPhone": null,
      "images": [
        "https://lid.zoocdn.com/645/430/f34190bb4f6bd7417b132c7f502cce4be409fc2c.jpg",
        "https://lid.zoocdn.com/645/430/b9318b00a96d8b44fd45f82bc80e0d70437df1e6.jpg",
        "https://lid.zoocdn.com/645/430/6ba52d7fb1a9d162993d06cad8a9dff807d54303.jpg",
        "https://lid.zoocdn.com/645/430/077ac194baae853ca0ab0d4ed58c71fc5825dff1.jpg",
        "https://lid.zoocdn.com/645/430/bba539f8400096ae0a4d702edb3c49a21b491517.jpg",
        "https://lid.zoocdn.com/645/430/f75411384d196adf4ba1072d1aac6faed56c2922.jpg",
        "https://lid.zoocdn.com/645/430/0297f042446d69a7c6fc3ea33d022e339e4d898d.jpg",
        "https://lid.zoocdn.com/645/430/2d3e5b51160a2b818c910d39941616f22fd2ebbe.jpg",
        "https://lid.zoocdn.com/645/430/2e35ed12cac50a05ca6e145b0960788a9e94ff70.jpg",
        "https://lid.zoocdn.com/645/430/9302c623646aefc5d3d1498730337d85feef6db2.jpg",
        "https://lid.zoocdn.com/645/430/4f22eb9d630d02b10674be98121b5fddfb91f3a9.jpg",
        "https://lid.zoocdn.com/645/430/9dda6200a396ab5cc70f20bf7c057e5768ab94df.jpg",
        "https://lid.zoocdn.com/645/430/235baee5bd426c647c8315f2c70f6aaefb02feb9.jpg",
        "https://lid.zoocdn.com/645/430/e486748381e6c07ad9f5a450c6002fd423c7d8c1.jpg",
        "https://lid.zoocdn.com/645/430/fda464d8db3a19573b15e8f2d477b3fa8206be1d.jpg"
      ],
      "sources": [
        {
          "portal": "Zoopla",
          "url": "https://www.zoopla.co.uk/for-sale/details/72650622/"
        }
      ],
      "lat": 50.41663565421549,
      "lon": -3.6912134759871997,
      "searchLocation": "Totnes",
      "searchLocations": [
        "Totnes"
      ],
      "autoRejected": false,
      "geoAccuracy": "postcode",
      "nearestAirport": {
        "name": "Exeter International Airport",
        "icao": "EGTE",
        "category": "airport",
        "usage": "commercial",
        "active": true,
        "distanceKm": 40.38102164109834,
        "distanceMiles": 25.09159579815092
      },
      "nearestAirstrip": {
        "name": "Halwell Airstrip",
        "icao": null,
        "category": "airstrip",
        "usage": "private",
        "active": false,
        "distanceKm": 5.828236845808926,
        "distanceMiles": 3.6214973571171383
      },
      "nearestHeliport": {
        "name": "Torquay Go-Kart circuit helipad",
        "icao": null,
        "category": "heliport",
        "usage": "private",
        "active": false,
        "distanceKm": 10.220867620855508,
        "distanceMiles": 6.350950734438608
      },
      "minAirportDistanceMiles": 3.6214973571171383,
      "flyoverRef": {
        "location": "London Gatwick Area",
        "flightsPerDay": 688.1,
        "seasonalFlag": "stable",
        "generatedAt": "2026-06-26T12:59:20.862Z"
      },
      "keywordsMatched": 0,
      "baselineComparison": {
        "airportsCount": 0,
        "airstripsCount": 2,
        "helipadsCount": 2,
        "airportsDiff": -4,
        "airstripsDiff": 2,
        "helipadsDiff": -2,
        "flightsPerDay": 688.1,
        "flightsDiffPct": 715
      },
      "isNew": true,
      "retrievedAt": "2026-07-23T09:57:23.571Z"
    },
    {
      "title": "3 bed property for sale",
      "price": 120000,
      "address": "Parkers Close, Totnes TQ9",
      "bedrooms": 3,
      "bathrooms": 1,
      "sqft": null,
      "type": "Property",
      "description": "Situated within close walking distance of the Town Centre and River Dart, is this three bedroom ground ...Listed on 21st Jul 2026",
      "postedDate": "Just added",
      "agent": null,
      "agentPhone": null,
      "images": [
        "https://lid.zoocdn.com/645/430/c1bdca71f873eae197aa545f1c4cc83ecd99f905.jpg",
        "https://lid.zoocdn.com/645/430/ed10b9744f6e5c6a4ac5e22fb378bfa953a7bd3e.jpg",
        "https://lid.zoocdn.com/645/430/2aa087a2af7849fffc7a05231bfe13a911f4d1e3.jpg",
        "https://lid.zoocdn.com/645/430/d201b9e9dacd29f3cb95ce9e949b73b82b462bdf.jpg",
        "https://lid.zoocdn.com/645/430/3d87f520b3ea5be3cdd9911dbcf0017887f8a7c6.jpg",
        "https://lid.zoocdn.com/645/430/1044d42e47e4cdf27f62f9d779c5264d9d2fad96.jpg",
        "https://lid.zoocdn.com/645/430/549b9abd9d721a12a38e2c2e5168848d0c9c4775.jpg",
        "https://lid.zoocdn.com/645/430/28f4435c4ddc5fd495fd0d4b01d9039284216580.jpg",
        "https://lid.zoocdn.com/645/430/a0c986ec23dce8b4151af233ee132cc64e120e48.jpg",
        "https://lid.zoocdn.com/645/430/192696de4e1f7df57cf1407d72031c9e8262f044.jpg"
      ],
      "sources": [
        {
          "portal": "Zoopla",
          "url": "https://www.zoopla.co.uk/for-sale/details/73774188/"
        }
      ],
      "lat": 50.41663565421549,
      "lon": -3.6912134759871997,
      "searchLocation": "Totnes",
      "searchLocations": [
        "Totnes"
      ],
      "autoRejected": false,
      "geoAccuracy": "postcode",
      "nearestAirport": {
        "name": "Exeter International Airport",
        "icao": "EGTE",
        "category": "airport",
        "usage": "commercial",
        "active": true,
        "distanceKm": 40.38102164109834,
        "distanceMiles": 25.09159579815092
      },
      "nearestAirstrip": {
        "name": "Halwell Airstrip",
        "icao": null,
        "category": "airstrip",
        "usage": "private",
        "active": false,
        "distanceKm": 5.828236845808926,
        "distanceMiles": 3.6214973571171383
      },
      "nearestHeliport": {
        "name": "Torquay Go-Kart circuit helipad",
        "icao": null,
        "category": "heliport",
        "usage": "private",
        "active": false,
        "distanceKm": 10.220867620855508,
        "distanceMiles": 6.350950734438608
      },
      "minAirportDistanceMiles": 3.6214973571171383,
      "flyoverRef": {
        "location": "London Gatwick Area",
        "flightsPerDay": 688.1,
        "seasonalFlag": "stable",
        "generatedAt": "2026-06-26T12:59:20.862Z"
      },
      "keywordsMatched": 0,
      "baselineComparison": {
        "airportsCount": 0,
        "airstripsCount": 2,
        "helipadsCount": 2,
        "airportsDiff": -4,
        "airstripsDiff": 2,
        "helipadsDiff": -2,
        "flightsPerDay": 688.1,
        "flightsDiffPct": 715
      },
      "isNew": true,
      "retrievedAt": "2026-07-23T09:57:23.571Z"
    },
    {
      "title": "2 bed end of terrace for sale",
      "price": 225000,
      "address": "Coldharbour, Bridgetown, Totnes, Devon TQ9",
      "bedrooms": 2,
      "bathrooms": null,
      "sqft": null,
      "type": "end of terrace",
      "description": "A charming two bedroom end of terrace home in the heart of Bridgetown, Totnes, offering a beautiful private garden and easy ...Listed on 23rd Apr 2026",
      "postedDate": null,
      "agent": null,
      "agentPhone": null,
      "images": [
        "https://lid.zoocdn.com/645/430/0c7c92ad447b127a1909dd436f9cc14f1985c34d.jpg",
        "https://lid.zoocdn.com/645/430/ba40274b57a4bfc13c1d54c0e62f1f41cb34344e.jpg",
        "https://lid.zoocdn.com/645/430/7a79b81d07240b4824db1bdcc20c30f081e17e04.jpg",
        "https://lid.zoocdn.com/645/430/fda0d3dfc7331d3614e1148cd9f8f577424f1248.jpg",
        "https://lid.zoocdn.com/645/430/e79c7aee8725877e1fe6e72d9860d9a503f6f2fd.jpg",
        "https://lid.zoocdn.com/645/430/16e354ec608e55ed7c5d646618a73bbdae03dbaf.jpg",
        "https://lid.zoocdn.com/645/430/97fbb080e9be059b5b40cc427943d719515fc039.jpg",
        "https://lid.zoocdn.com/645/430/025ad6a70b9c8fc8f7fcfc844c86a18b45e709cf.jpg",
        "https://lid.zoocdn.com/645/430/1ee57b189af7bc98a0fa07a8e781f1588215e8f7.jpg",
        "https://lid.zoocdn.com/645/430/afbfe275da1878b22d93ad0741bd525e44b322b1.jpg",
        "https://lid.zoocdn.com/645/430/c680e92cd4f905c04782a85cfb4d15f701580534.jpg",
        "https://lid.zoocdn.com/645/430/16e459e6d92a947142236ecff6093c78689d3800.jpg",
        "https://lid.zoocdn.com/645/430/2eceee2ad9596b8f649beb39c079a9cf7e3e2fd8.jpg",
        "https://lid.zoocdn.com/645/430/009c62429b35c69328379d091ff0feeeb7934611.jpg",
        "https://lid.zoocdn.com/645/430/c3c21aab5d5bbe1619b782fedf96af102706f820.jpg"
      ],
      "sources": [
        {
          "portal": "Zoopla",
          "url": "https://www.zoopla.co.uk/for-sale/details/73008231/"
        }
      ],
      "lat": 50.41663565421549,
      "lon": -3.6912134759871997,
      "searchLocation": "Totnes",
      "searchLocations": [
        "Totnes"
      ],
      "autoRejected": true,
      "geoAccuracy": "postcode",
      "nearestAirport": {
        "name": "Exeter International Airport",
        "icao": "EGTE",
        "category": "airport",
        "usage": "commercial",
        "active": true,
        "distanceKm": 40.38102164109834,
        "distanceMiles": 25.09159579815092
      },
      "nearestAirstrip": {
        "name": "Halwell Airstrip",
        "icao": null,
        "category": "airstrip",
        "usage": "private",
        "active": false,
        "distanceKm": 5.828236845808926,
        "distanceMiles": 3.6214973571171383
      },
      "nearestHeliport": {
        "name": "Torquay Go-Kart circuit helipad",
        "icao": null,
        "category": "heliport",
        "usage": "private",
        "active": false,
        "distanceKm": 10.220867620855508,
        "distanceMiles": 6.350950734438608
      },
      "minAirportDistanceMiles": 3.6214973571171383,
      "flyoverRef": {
        "location": "London Gatwick Area",
        "flightsPerDay": 688.1,
        "seasonalFlag": "stable",
        "generatedAt": "2026-06-26T12:59:20.862Z"
      },
      "keywordsMatched": 1,
      "baselineComparison": {
        "airportsCount": 0,
        "airstripsCount": 2,
        "helipadsCount": 2,
        "airportsDiff": -4,
        "airstripsDiff": 2,
        "helipadsDiff": -2,
        "flightsPerDay": 688.1,
        "flightsDiffPct": 715
      },
      "isNew": true,
      "retrievedAt": "2026-07-23T09:57:23.571Z"
    },
    {
      "title": "2 bed property for sale",
      "price": 195950,
      "address": "Culverdale, Totnes TQ9",
      "bedrooms": 2,
      "bathrooms": 1,
      "sqft": null,
      "type": "Property",
      "description": "a viewing, when calling please quote CS1097 | No upward chain | End terraced home | Entrance hall | Sitting room | ...Listed on 29th Aug 2025",
      "postedDate": "Reduced",
      "agent": null,
      "agentPhone": null,
      "images": [
        "https://lid.zoocdn.com/645/430/748c8270c4b9f1bc57995e06c164285c02e941c7.jpg"
      ],
      "sources": [
        {
          "portal": "Zoopla",
          "url": "https://www.zoopla.co.uk/for-sale/details/71179359/"
        }
      ],
      "lat": 50.41663565421549,
      "lon": -3.6912134759871997,
      "searchLocation": "Totnes",
      "searchLocations": [
        "Totnes"
      ],
      "autoRejected": false,
      "geoAccuracy": "postcode",
      "nearestAirport": {
        "name": "Exeter International Airport",
        "icao": "EGTE",
        "category": "airport",
        "usage": "commercial",
        "active": true,
        "distanceKm": 40.38102164109834,
        "distanceMiles": 25.09159579815092
      },
      "nearestAirstrip": {
        "name": "Halwell Airstrip",
        "icao": null,
        "category": "airstrip",
        "usage": "private",
        "active": false,
        "distanceKm": 5.828236845808926,
        "distanceMiles": 3.6214973571171383
      },
      "nearestHeliport": {
        "name": "Torquay Go-Kart circuit helipad",
        "icao": null,
        "category": "heliport",
        "usage": "private",
        "active": false,
        "distanceKm": 10.220867620855508,
        "distanceMiles": 6.350950734438608
      },
      "minAirportDistanceMiles": 3.6214973571171383,
      "flyoverRef": {
        "location": "London Gatwick Area",
        "flightsPerDay": 688.1,
        "seasonalFlag": "stable",
        "generatedAt": "2026-06-26T12:59:20.862Z"
      },
      "keywordsMatched": 0,
      "baselineComparison": {
        "airportsCount": 0,
        "airstripsCount": 2,
        "helipadsCount": 2,
        "airportsDiff": -4,
        "airstripsDiff": 2,
        "helipadsDiff": -2,
        "flightsPerDay": 688.1,
        "flightsDiffPct": 715
      },
      "isNew": true,
      "retrievedAt": "2026-07-23T09:57:23.571Z"
    },
    {
      "title": "3 bed detached house for sale",
      "price": 80000,
      "address": "78 Higher Westonfields, Totnes, Devon TQ9",
      "bedrooms": 3,
      "bathrooms": null,
      "sqft": null,
      "type": "Detached House",
      "description": "",
      "postedDate": "Reduced",
      "agent": null,
      "agentPhone": null,
      "images": [
        "https://lid.zoocdn.com/645/430/99c7bc13b685151b278cd1dca1796ae09bf78579.jpg"
      ],
      "sources": [
        {
          "portal": "Zoopla",
          "url": "https://www.zoopla.co.uk/for-sale/details/73502930/"
        }
      ],
      "lat": 50.41663565421549,
      "lon": -3.6912134759871997,
      "searchLocation": "Totnes",
      "searchLocations": [
        "Totnes"
      ],
      "autoRejected": false,
      "geoAccuracy": "postcode",
      "nearestAirport": {
        "name": "Exeter International Airport",
        "icao": "EGTE",
        "category": "airport",
        "usage": "commercial",
        "active": true,
        "distanceKm": 40.38102164109834,
        "distanceMiles": 25.09159579815092
      },
      "nearestAirstrip": {
        "name": "Halwell Airstrip",
        "icao": null,
        "category": "airstrip",
        "usage": "private",
        "active": false,
        "distanceKm": 5.828236845808926,
        "distanceMiles": 3.6214973571171383
      },
      "nearestHeliport": {
        "name": "Torquay Go-Kart circuit helipad",
        "icao": null,
        "category": "heliport",
        "usage": "private",
        "active": false,
        "distanceKm": 10.220867620855508,
        "distanceMiles": 6.350950734438608
      },
      "minAirportDistanceMiles": 3.6214973571171383,
      "flyoverRef": {
        "location": "London Gatwick Area",
        "flightsPerDay": 688.1,
        "seasonalFlag": "stable",
        "generatedAt": "2026-06-26T12:59:20.862Z"
      },
      "keywordsMatched": 0,
      "baselineComparison": {
        "airportsCount": 0,
        "airstripsCount": 2,
        "helipadsCount": 2,
        "airportsDiff": -4,
        "airstripsDiff": 2,
        "helipadsDiff": -2,
        "flightsPerDay": 688.1,
        "flightsDiffPct": 715
      },
      "isNew": true,
      "retrievedAt": "2026-07-23T09:57:23.571Z"
    },
    {
      "title": "3 bed property for sale",
      "price": 260000,
      "address": "Whiteley Avenue, Totnes, Devon TQ9",
      "bedrooms": 3,
      "bathrooms": 2,
      "sqft": null,
      "type": "Property",
      "description": "A well-presented three-bedroom home situated in a popular residential location on Whiteley Avenue, offering spacious and ...Listed on 13th Jul 2026",
      "postedDate": null,
      "agent": null,
      "agentPhone": null,
      "images": [
        "https://lid.zoocdn.com/645/430/68a300cd02e539a52cd8cb1fe8012b4857543cd8.jpg"
      ],
      "sources": [
        {
          "portal": "Zoopla",
          "url": "https://www.zoopla.co.uk/for-sale/details/73705832/"
        }
      ],
      "lat": 50.41663565421549,
      "lon": -3.6912134759871997,
      "searchLocation": "Totnes",
      "searchLocations": [
        "Totnes"
      ],
      "autoRejected": false,
      "geoAccuracy": "postcode",
      "nearestAirport": {
        "name": "Exeter International Airport",
        "icao": "EGTE",
        "category": "airport",
        "usage": "commercial",
        "active": true,
        "distanceKm": 40.38102164109834,
        "distanceMiles": 25.09159579815092
      },
      "nearestAirstrip": {
        "name": "Halwell Airstrip",
        "icao": null,
        "category": "airstrip",
        "usage": "private",
        "active": false,
        "distanceKm": 5.828236845808926,
        "distanceMiles": 3.6214973571171383
      },
      "nearestHeliport": {
        "name": "Torquay Go-Kart circuit helipad",
        "icao": null,
        "category": "heliport",
        "usage": "private",
        "active": false,
        "distanceKm": 10.220867620855508,
        "distanceMiles": 6.350950734438608
      },
      "minAirportDistanceMiles": 3.6214973571171383,
      "flyoverRef": {
        "location": "London Gatwick Area",
        "flightsPerDay": 688.1,
        "seasonalFlag": "stable",
        "generatedAt": "2026-06-26T12:59:20.862Z"
      },
      "keywordsMatched": 0,
      "baselineComparison": {
        "airportsCount": 0,
        "airstripsCount": 2,
        "helipadsCount": 2,
        "airportsDiff": -4,
        "airstripsDiff": 2,
        "helipadsDiff": -2,
        "flightsPerDay": 688.1,
        "flightsDiffPct": 715
      },
      "isNew": true,
      "retrievedAt": "2026-07-23T09:57:23.571Z"
    }
  ],
  "portalLinks": [
    {
      "portal": "Zoopla",
      "url": "https://www.zoopla.co.uk/for-sale/property/tq9-5hr/?q=garden&price_max=450000&beds_min=2",
      "searchLocation": "Totnes"
    },
    {
      "portal": "OnTheMarket",
      "url": "https://www.onthemarket.com/for-sale/property/tq9-5hr/?q=garden&min-bedrooms=2&max-price=450000",
      "searchLocation": "Totnes"
    },
    {
      "portal": "Durrants",
      "url": "https://durrants.com/properties/?department=residential-sales&view=list&address_keyword=TQ9%205HR&radius=20&minimum_bedrooms=2&maximum_price=450000",
      "searchLocation": "Totnes"
    },
    {
      "portal": "Rightmove",
      "url": "https://www.rightmove.co.uk/property-for-sale/find.html?locationIdentifier=REGION%5E1353&radius=40.0&keywords=garden&maxPrice=450000&minBedrooms=2&includeSSTC=false",
      "searchLocation": "Totnes"
    },
    {
      "portal": "Savills",
      "url": "https://search.savills.com/list?SearchList=Id_5201+Category_SBuy&Tenure=GRS_T_B&SortOrder=SO_PCDD&SearchLocation=TQ9%205HR&MinBedrooms=2&MaxPrice=450000",
      "searchLocation": "Totnes"
    },
    {
      "portal": "Strutt & Parker",
      "url": "https://www.struttandparker.com/find-a-property?search=TQ9%205HR&minbeds=2&maxprice=450000",
      "searchLocation": "Totnes"
    },
    {
      "portal": "Jackson-Stops",
      "url": "https://www.jackson-stops.co.uk/properties/search?channel=sales&locations[0]=TQ9%205HR&minBeds=2&maxPrice=450000",
      "searchLocation": "Totnes"
    },
    {
      "portal": "Winkworth",
      "url": "https://www.winkworth.co.uk/properties?search_location=TQ9%205HR&min_beds=2&keywords=garden&max_price=450000",
      "searchLocation": "Totnes"
    }
  ],
  "dupePassAt": "2026-07-23T11:15:19.037Z"
}